.gitignore
.readthedocs.yaml
CITATION.cff
LICENSE
MANIFEST.in
README.md
headerlicense.txt
pyproject.toml
requirements.txt
setup.py
.github/workflows/python-publish.yml
docs/Makefile
docs/make.bat
docs/requirements.txt
docs/source/api.rst
docs/source/changelog.rst
docs/source/conf.py
docs/source/dev.rst
docs/source/index.rst
docs/source/installation.rst
docs/source/introduction.rst
docs/source/tutorial.rst
docs/source/_static/favicon.ico
docs/source/_static/shxarraylogo_dark.png
docs/source/_static/shxarraylogo_light.png
docs/source/_templates/module.rst_t
docs/source/_templates/package.rst_t
docs/source/_templates/toc.rst_t
docs/source/logo_etc/favicon.ico
docs/source/logo_etc/logo_base.png
docs/source/logo_etc/logo_base.xcf
docs/source/logo_etc/make_logobase.ipynb
docs/source/logo_etc/makefavicon
docs/source/logo_etc/shxarray_logo_wtext.svg
docs/source/logo_etc/shxarray_logo_wtext_dark.png
docs/source/logo_etc/shxarray_logo_wtext_light.png
docs/source/logo_etc/shxarraylogo_dark.png
docs/source/logo_etc/shxarraylogo_light.png
docs/source/notebooks/.gitignore
docs/source/notebooks/Geometry2sphericalHarmonics.ipynb
docs/source/notebooks/OceanMask.ipynb
docs/source/notebooks/SealevelEquation.ipynb
docs/source/notebooks/TerrestrialWaterStorage.ipynb
docs/source/notebooks/visualize_filter.ipynb
sample-data/GRACEDataSample_2020.sql
sample-data/GRACEDataSample_2020_files.tgz
sample-data/dump-grace.py
src/builtin_backend/.gitignore
src/builtin_backend/Gaunt.hpp
src/builtin_backend/Helpers.hpp
src/builtin_backend/Legendre.hpp
src/builtin_backend/Legendre_nm.hpp
src/builtin_backend/Wigner3j.hpp
src/builtin_backend/Ynm.hpp
src/builtin_backend/analysis.pyx
src/builtin_backend/gaunt.pxd
src/builtin_backend/gaunt.pyx
src/builtin_backend/legendre.pxd
src/builtin_backend/legendre.pyx
src/builtin_backend/shindex.pxd
src/builtin_backend/shlib.cpp
src/builtin_backend/shlib.pyx
src/builtin_backend/sinex.pyx
src/builtin_backend/synthesis.pyx
src/builtin_backend/wigner3j.pxd
src/shxarray.egg-info/PKG-INFO
src/shxarray.egg-info/SOURCES.txt
src/shxarray.egg-info/dependency_links.txt
src/shxarray.egg-info/entry_points.txt
src/shxarray.egg-info/requires.txt
src/shxarray.egg-info/top_level.txt
