Metadata-Version: 2.4
Name: shxarray
Version: 1.4.0
Summary: Spherical harmonic extension for Xarray
Author-email: Roelof Rietbroek <r.rietbroek@utwente.nl>
Project-URL: Homepage, https://github.com/ITC-Water-Resources/shxarray
Project-URL: Bug Tracker, https://github.com/ITC-Water-Resources/shxarray/issues
Classifier: Programming Language :: Python :: 3
Classifier: License :: OSI Approved :: Apache Software License
Classifier: Operating System :: POSIX :: Linux
Classifier: Intended Audience :: Science/Research
Classifier: Topic :: Scientific/Engineering
Classifier: Development Status :: 1 - Planning
Requires-Python: >=3.8
License-File: LICENSE
Requires-Dist: pandas>=2.0
Requires-Dist: pyaml>=23.9.0
Requires-Dist: scipy
Requires-Dist: xarray>=2023.1.0
Requires-Dist: numpy
Requires-Dist: numba
Requires-Dist: sparse
Requires-Dist: importlib_metadata
Requires-Dist: requests
Requires-Dist: openpyxl
Requires-Dist: geopandas
Provides-Extra: dask
Requires-Dist: dask>=2022.9.2; extra == "dask"
Provides-Extra: rapidgzip
Requires-Dist: rapidgzip; extra == "rapidgzip"
Dynamic: license-file
